pyhacrf_datamade-0.2.8.dist-info/RECORD
pyhacrf_datamade-0.2.8.dist-info/WHEEL
pyhacrf_datamade-0.2.8.dist-info/top_level.txt
pyhacrf_datamade-0.2.8.dist-info/METADATA
pyhacrf_datamade-0.2.8.dist-info/licenses/LICENSE
pyhacrf/algorithms.pypy311-pp73-darwin.so
pyhacrf/__init__.py
pyhacrf/feature_extraction.py
pyhacrf/state_machine.py
pyhacrf/adjacent.pypy311-pp73-darwin.so
pyhacrf/pyhacrf.py
