Metadata-Version: 2.4
Name: pyhacrf-datamade
Version: 0.2.8
Summary: Hidden alignment conditional random field, a discriminative string edit distance
Home-page: https://github.com/datamade/pyhacrf
Author: Dirko Coetsee
Author-email: dpcoetsee@gmail.com
Maintainer: Forest Gregg
Maintainer-email: fgregg@gmail.com
Classifier: Intended Audience :: Science/Research
Classifier: License :: OSI Approved :: BSD License
Classifier: Operating System :: OS Independent
Classifier: Programming Language :: Python
Classifier: Topic :: Scientific/Engineering
Requires-Python: >=3.9
License-File: LICENSE
Requires-Dist: numpy>=1.14.1; python_version < "3.6"
Requires-Dist: numpy>=1.15.0; python_version == "3.7"
Requires-Dist: numpy>=1.17.3; python_version == "3.8"
Requires-Dist: numpy; python_version > "3.8"
Requires-Dist: PyLBFGS>=0.1.3
Dynamic: author
Dynamic: author-email
Dynamic: classifier
Dynamic: description
Dynamic: home-page
Dynamic: license-file
Dynamic: maintainer
Dynamic: maintainer-email
Dynamic: requires-dist
Dynamic: requires-python
Dynamic: summary
